lofty/__init__.py
lofty/client.py
lofty/client_auth.py
lofty/constants.py
lofty/date_functions.py
lofty/pagination_options.py
lofty/transaction_manager.py
lofty/auth/__init__.py
lofty/auth/aws_cognito_idp.py
lofty/requests/__init__.py
lofty/requests/withdrawal.py
lofty/responses/__init__.py
lofty/responses/api_response.py
lofty/responses/bank_data.py
lofty/responses/countries.py
lofty/responses/exchange_user_info.py
lofty/responses/payment_methods_list.py
lofty/responses/pending_orders.py
lofty/responses/property_info.py
lofty/responses/property_orderbook.py
lofty/responses/stats_summary.py
lofty/responses/transaction.py
lofty/responses/transaction_summary.py
lofty/responses/transactions_by_user.py
lofty/responses/user.py
lofty/responses/user_status_summary.py
lofty/responses/verification_token.py
lofty/responses/auth/__init__.py
lofty/responses/auth/aws_credentials.py
lofty/responses/auth/device_metadata.py
lofty/responses/auth/sign_in_response.py
lofty/transactions/__init__.py
lofty/transactions/withdrawal_method.py
myb_lofty_api-2.5.1.dist-info/LICENSE
myb_lofty_api-2.5.1.dist-info/METADATA
myb_lofty_api-2.5.1.dist-info/WHEEL
myb_lofty_api-2.5.1.dist-info/top_level.txt
myb_lofty_api-2.5.1.dist-info/RECORD
