Metadata-Version: 2.1
Name: myb-lofty-api
Version: 2.5.1
Summary: Unofficial Python library for communicating with the Lofty AI (Real Estate) API
Home-page: https://github.com/mine-your-business/myb-lofty-python-api
Author: Dev Piekstra
Author-email: piekstra.dev@gmail.com
License: GPL-3
Classifier: Programming Language :: Python :: 3
Classifier: License :: OSI Approved :: GNU General Public License v3 (GPLv3)
Classifier: Operating System :: OS Independent
Requires-Python: >=3.9
License-File: LICENSE
Requires-Dist: requests (<3,>=2)
Requires-Dist: python-dateutil (>=2)
